{
  "main": {
    "id": "5324373015726ba8",
    "type": "split",
    "children": [
      {
        "id": "4509724f8bf84da7",
        "type": "tabs",
        "children": [
          {
            "id": "e7a7b303c61786dc",
            "type": "leaf",
            "state": {
              "type": "markdown",
              "state": {
                "file": "大纲/大纲.md",
                "mode": "source",
                "source": false
              },
              "icon": "lucide-file",
              "title": "大纲"
            }
          }
        ]
      }
    ],
    "direction": "vertical"
  },
  "left": {
    "id": "90d374bd46072ae4",
    "type": "split",
    "children": [
      {
        "id": "15e08a2cd3845a30",
        "type": "tabs",
        "children": [
          {
            "id": "71f5f20815de2c7d",
            "type": "leaf",
            "state": {
              "type": "file-explorer",
              "state": {
                "sortOrder": "alphabetical"
              },
              "icon": "lucide-folder-closed",
              "title": "文件列表"
            }
          },
          {
            "id": "6143f7e9cf10e680",
            "type": "leaf",
            "state": {
              "type": "search",
              "state": {
                "query": "重构",
                "matchingCase": false,
                "explainSearch": false,
                "collapseAll": false,
                "extraContext": false,
                "sortOrder": "alphabetical"
              },
              "icon": "lucide-search",
              "title": "搜索"
            }
          },
          {
            "id": "92f68a936ebd0bd8",
            "type": "leaf",
            "state": {
              "type": "bookmarks",
              "state": {},
              "icon": "lucide-bookmark",
              "title": "书签"
            }
          },
          {
            "id": "16b6c5bc2107c4ca",
            "type": "leaf",
            "state": {
              "type": "recent-files",
              "state": {},
              "icon": "clock",
              "title": "Recent Files"
            }
          }
        ]
      }
    ],
    "direction": "horizontal",
    "width": 252
  },
  "right": {
    "id": "c849f9fe049669ba",
    "type": "split",
    "children": [
      {
        "id": "0fcb9ac62d3c1956",
        "type": "tabs",
        "children": [
          {
            "id": "5cf384f2f32fe777",
            "type": "leaf",
            "state": {
              "type": "advanced-tables-toolbar",
              "state": {},
              "icon": "spreadsheet",
              "title": "Advanced Tables"
            }
          },
          {
            "id": "cc49229fa06ee41e",
            "type": "leaf",
            "state": {
              "type": "tag",
              "state": {
                "sortOrder": "frequency",
                "useHierarchy": true
              },
              "icon": "lucide-tags",
              "title": "标签"
            }
          },
          {
            "id": "e9b2f9d0fb8d6f7c",
            "type": "leaf",
            "state": {
              "type": "backlink",
              "state": {
                "file": "前端/工程化.md",
                "collapseAll": false,
                "extraContext": false,
                "sortOrder": "alphabetical",
                "showSearch": false,
                "searchQuery": "",
                "backlinkCollapsed": false,
                "unlinkedCollapsed": true
              },
              "icon": "links-coming-in",
              "title": "工程化 的反向链接列表"
            }
          },
          {
            "id": "da58d73bfd1565f3",
            "type": "leaf",
            "state": {
              "type": "outgoing-link",
              "state": {
                "file": "大纲/大纲.md",
                "linksCollapsed": false,
                "unlinkedCollapsed": true
              },
              "icon": "links-going-out",
              "title": "大纲 的出链列表"
            }
          },
          {
            "id": "c8b36a9920cc263f",
            "type": "leaf",
            "state": {
              "type": "calendar",
              "state": {},
              "icon": "calendar-with-checkmark",
              "title": "Calendar"
            }
          },
          {
            "id": "af96eae4f639d271",
            "type": "leaf",
            "state": {
              "type": "quiet-outline",
              "state": {},
              "icon": "lines-of-text",
              "title": "Quiet Outline"
            }
          }
        ],
        "currentTab": 5
      }
    ],
    "direction": "horizontal",
    "width": 252
  },
  "left-ribbon": {
    "hiddenItems": {
      "switcher:打开快速切换": true,
      "templates:插入模板": true,
      "command-palette:打开命令面板": true,
      "table-editor-obsidian:Advanced Tables Toolbar": false,
      "remotely-save:Remotely Save": false,
      "obsidian-excalidraw-plugin:新建绘图文件": false,
      "templater-obsidian:Templater": false,
      "homepage:Open homepage": false,
      "obsidian-git:Open Git source control": false,
      "obsidian-kanban:创建新看板": false,
      "obsidian-advanced-slides:Show Slide Preview": false,
      "omnisearch:Omnisearch": false,
      "surfing:surfing-bookmark-manager": false,
      "notion-like-tables:Create loom": false
    }
  },
  "active": "e7a7b303c61786dc",
  "lastOpenFiles": [
    "output/前端不常用/tsconfig.md",
    "大纲/大纲.md",
    "output/shell.md",
    "output/业务.md",
    "output/性能&错误监控.md",
    "output/代码实现.md",
    "output/qiankun.md",
    "output/assets/WEBRESOURCE8d9068a993116e9724ff3ffbc7061099bee332e41f444312d6ddf44eaaa60403.png",
    "output/监控（性能&错误）.md",
    "output/assets/WEBRESOURCE6803799c068d25899f9b5355bd7fd412截图.png",
    "output/assets/WEBRESOURCE5fd93f9398090b3297bdc05184fd06c3截图.png",
    "output/assets/WEBRESOURCEf3dc81b697e3b89d14b4840b93f2d87b截图.png",
    "output/assets/WEBRESOURCEeded12ff66cb9b87e3d429edb8d2101astickPicture.png",
    "output/assets/WEBRESOURCE2da2befc97ff2f2edabc97a2f9a6c58aimage.png",
    "output/assets/WEBRESOURCE11677bb589d8344a04f5bc7d627afbda截图.png",
    "output/assets/WEBRESOURCEcb203559092a66c5a1e2a2e9591073e1截图.png",
    "output/assets/WEBRESOURCE73013823cdafadaaa95a4db48e77735a截图.png",
    "output/assets/WEBRESOURCE5871a565b0eaf0f95687dd46279e5237截图.png",
    "output/微前端方案.md",
    "output/工程化.md",
    "output/前端组件/组件.md",
    "output/前端组件",
    "output/前端不常用/性能优化.md",
    "output/住院护士.excalidraw.md",
    "output/前端不常用/性能优化.md~",
    "output/HIS.md",
    "output/前端不常用/设计模式.md",
    "output/前端不常用/知识补充.md",
    "output/前端不常用/正则.md",
    "output/前端不常用/单测.md",
    "output/前端不常用/webpack.md",
    "output/前端不常用/vue3.md",
    "output/前端不常用/vite.md~",
    "output/前端不常用/vite.md",
    "output/前端不常用/uniapp.md",
    "output/前端不常用/tsconfig.json.md",
    "output/前端不常用/package.md",
    "output/前端不常用/storybook.md",
    "output/前端不常用/images",
    "output/前端不常用/echarts.md",
    "output/前端不常用",
    "output/electron.md~",
    "output/antv/images",
    "output/antv",
    "output/images",
    "output/assets",
    "Excalidraw/未命名.canvas"
  ]
}